nodenormalizer_mcp/server.py
nodenormalizer_mcp-0.1.1.dist-info/METADATA
nodenormalizer_mcp-0.1.1.dist-info/WHEEL
nodenormalizer_mcp-0.1.1.dist-info/entry_points.txt
nodenormalizer_mcp-0.1.1.dist-info/RECORD
